py_bulk_image_compressor/__init__.py
py_bulk_image_compressor/main.py
py_bulk_image_compressor/components/__init__.py
py_bulk_image_compressor/components/imageCompressor.py
py_bulk_image_compressor/components/localColors.py
py_bulk_image_compressor/components/mainClasses.py
py_bulk_image_compressor/components/mainFunctions.py
py_bulk_image_compressor/components/setConfigurations.py
py_bulk_image_compressor/data/__init__.py
py_bulk_image_compressor/resources/configurations.ini
py_bulk_image_compressor/tests/__init__.py
py_bulk_image_compressor/tests/test_imageCompressor.py
py_bulk_image_compressor/tests/test_main.py
py_bulk_image_compressor/tests/test_mainFunctions.py
py_bulk_image_compressor/tests/test_setConfigurations.py
py_bulk_image_compressor-1.0.8.dist-info/licenses/LICENSE
py_bulk_image_compressor-1.0.8.dist-info/METADATA
py_bulk_image_compressor-1.0.8.dist-info/WHEEL
py_bulk_image_compressor-1.0.8.dist-info/entry_points.txt
py_bulk_image_compressor-1.0.8.dist-info/top_level.txt
py_bulk_image_compressor-1.0.8.dist-info/RECORD
