Metadata-Version: 2.4
Name: py-bulk-image-compressor
Version: 1.0.8
Summary: A Python bulk image compressor and resizer
Home-page: https://github.com/georgekhananaev/py-image-compressor
Author: George Khananaev
Author-email: george.khananaev@gmail.com
Classifier: Programming Language :: Python :: 3
Classifier: License :: OSI Approved :: MIT License
License-File: LICENSE
Requires-Dist: Pillow>=11.1.0
Requires-Dist: tqdm>=4.67.1
Requires-Dist: pillow-heif>=0.21.0
Requires-Dist: pillow-avif-plugin>=1.4.6
Dynamic: author
Dynamic: author-email
Dynamic: classifier
Dynamic: description
Dynamic: description-content-type
Dynamic: home-page
Dynamic: license-file
Dynamic: requires-dist
Dynamic: summary
